{"Albania":"e-visa","Algeria":"visa required","Andorra":"visa required","Angola":"visa required","Antigua and Barbuda":"90","Argentina":"90","Armenia":"180","Australia":"e-visa","Austria":"visa required","Azerbaijan":"e-visa","Bahamas":"90","Bahrain":"visa on arrival","Bangladesh":"visa on arrival","Barbados":"90","Belarus":"30","Belgium":"visa required","Belize":"visa required","Benin":"e-visa","Bhutan":"e-visa","Bolivia":"90","Bosnia and Herzegovina":"visa required","Botswana":"e-visa","Brazil":"90","Brunei":"visa required","Bulgaria":"visa required","Burkina Faso":"e-visa","Burundi":"visa on arrival","Cambodia":"visa on arrival","Cameroon":"e-visa","Canada":"visa required","Cape Verde":"visa on arrival","Central African Republic":"visa required","Chad":"e-visa","Chile":"90","China":"30","Colombia":"90","Comoros":"visa on arrival","Congo":"visa required","DR Congo":"e-visa","Costa Rica":"visa required","Ivory Coast":"eta","Croatia":"visa required","Cuba":"e-visa","Cyprus":"visa required","Czech Republic":"visa required","Denmark":"visa required","Djibouti":"visa on arrival","Dominica":"21","Dominican Republic":"30","Ecuador":"-1","Egypt":"visa on arrival","El Salvador":"180","Equatorial Guinea":"e-visa","Eritrea":"visa required","Estonia":"visa required","Swaziland":"visa required","Ethiopia":"e-visa","Fiji":"visa required","Finland":"visa required","France":"visa required","Gabon":"e-visa","Gambia":"visa required","Georgia":"360","Germany":"visa required","Ghana":"visa required","Greece":"visa required","Grenada":"90","Guatemala":"visa required","Guinea":"e-visa","Guinea-Bissau":"visa on arrival","Guyana":"90","Haiti":"90","Honduras":"90","Hong Kong":"90","Hungary":"visa required","Iceland":"visa required","India":"e-visa","Indonesia":"visa on arrival","Iran":"visa on arrival","Iraq":"e-visa","Ireland":"visa required","Israel":"eta","Italy":"visa required","Jamaica":"30","Japan":"visa required","Jordan":"visa on arrival","Kazakhstan":"30","Kenya":"eta","Kiribati":"visa required","Kosovo":"visa required","Kuwait":"visa required","Kyrgyzstan":"e-visa","Laos":"visa on arrival","Latvia":"visa required","Lebanon":"visa required","Lesotho":"visa required","Liberia":"e-visa","Libya":"e-visa","Liechtenstein":"visa required","Lithuania":"visa required","Luxembourg":"visa required","Macao":"30","Madagascar":"visa on arrival","Malawi":"visa on arrival","Malaysia":"30","Maldives":"visa on arrival","Mali":"visa required","Malta":"visa required","Marshall Islands":"visa on arrival","Mauritania":"e-visa","Mauritius":"visa on arrival","Mexico":"visa required","Micronesia":"30","Moldova":"e-visa","Monaco":"visa required","Mongolia":"30","Montenegro":"visa required","Morocco":"visa required","Mozambique":"visa on arrival","Myanmar":"e-visa","Namibia":"visa on arrival","Nauru":"visa required","Nepal":"visa on arrival","Netherlands":"visa required","New Zealand":"visa required","Nicaragua":"90","Niger":"visa required","Nigeria":"e-visa","North Korea":"visa required","North Macedonia":"visa required","Norway":"visa required","Oman":"visa on arrival","Pakistan":"e-visa","Palau":"visa on arrival","Palestine":"visa free","Panama":"90","Papua New Guinea":"eta","Paraguay":"90","Peru":"180","Philippines":"30","Poland":"visa required","Portugal":"visa required","Qatar":"visa on arrival","Romania":"visa required","Russia":"90","Rwanda":"visa on arrival","Saint Kitts and Nevis":"eta","Saint Lucia":"visa on arrival","Samoa":"visa on arrival","San Marino":"visa required","Sao Tome and Principe":"e-visa","Saudi Arabia":"e-visa","Senegal":"visa required","Serbia":"visa required","Seychelles":"90","Sierra Leone":"e-visa","Singapore":"30","Slovakia":"visa required","Slovenia":"visa required","Solomon Islands":"visa required","Somalia":"e-visa","South Africa":"90","South Korea":"eta","South Sudan":"e-visa","Spain":"visa required","Sri Lanka":"visa on arrival","Saint Vincent and the Grenadines":"90","Sudan":"visa required","Suriname":"eta","Sweden":"visa required","Switzerland":"visa required","Syria":"e-visa","Taiwan":"e-visa","Tajikistan":"30","Tanzania":"visa on arrival","Thailand":"60","Timor-Leste":"visa on arrival","Togo":"e-visa","Tonga":"visa required","Trinidad and Tobago":"90","Tunisia":"visa required","Turkmenistan":"visa required","Tuvalu":"visa on arrival","Turkey":"90","Uganda":"e-visa","Ukraine":"90","United Arab Emirates":"90","United Kingdom":"visa required","United States":"visa required","Uruguay":"90","Uzbekistan":"e-visa","Vanuatu":"e-visa","Vatican":"visa required","Venezuela":"90","Vietnam":"e-visa","Yemen":"visa required","Zambia":"visa on arrival","Zimbabwe":"visa on arrival","Afghanistan":"visa required"}